setup.py
IIPDarknet.egg-info/PKG-INFO
IIPDarknet.egg-info/SOURCES.txt
IIPDarknet.egg-info/dependency_links.txt
IIPDarknet.egg-info/top_level.txt
darknet/Detection.py
darknet/__init__.py