Metadata-Version: 1.1
Name: IIPDarknet
Version: 0.1.0
Summary: Algorithm for object detection using YOLOv3.
Home-page: http://iip.whu.edu.cn/GitLab/wangsihan/8.1Platform.git
Author: Huairui
Author-email: wanghr827@foxmail.com
License: BSD License
Platform: Linux
Classifier: Intended Audience :: Developers
Classifier: License :: OSI Approved :: BSD License
Classifier: Programming Language :: Python
Classifier: Programming Language :: Python :: Implementation
Classifier: Programming Language :: Python :: 2.7
Classifier: Topic :: Software Development :: Libraries
